azul_game_engine/action_not_allowed_exception.py
azul_game_engine/bag.py
azul_game_engine/board.py
azul_game_engine/center.py
azul_game_engine/factory_display.py
azul_game_engine/floor.py
azul_game_engine/game.py
azul_game_engine/lid.py
azul_game_engine/pattern_line.py
azul_game_engine/player.py
azul_game_engine/tile.py
azul_game_engine/wall.py
azul_game_engine-1.0.2.dist-info/licenses/LICENSE
azul_game_engine-1.0.2.dist-info/METADATA
azul_game_engine-1.0.2.dist-info/WHEEL
azul_game_engine-1.0.2.dist-info/top_level.txt
azul_game_engine-1.0.2.dist-info/RECORD
